{
    "name": "day9Office",
    "image": "Rex",
    "position": 0,
    "anchor": { "x": 0.4, "y": 0.33 },
    "triggerType": "Auto",
    "chatList": [
        {
            "$type": "TalkParagraph, Assembly-CSharp",
            "talker": "클로버",
            "text":"안녕하세요! 렉스씨!",
            "characterL": {
                "fileName": "Klayton_CG",
                "index": 0
            },
            "characterR": {
                "fileName": "Rex",
                "index": 3
            } 
        },
        {
            "$type": "TalkParagraph, Assembly-CSharp",
            "talker": "렉스",
            "text":"엇! 클로버님. 어찌 귀하신 분이 이렇게 누추하신 곳에...",
            "characterL": {
                "fileName": "Klayton_CG",
                "index": 0
            },
            "characterR": {
                "fileName": "Rex",
                "index": 6
            } 
        },
        {
            "$type": "TalkParagraph, Assembly-CSharp",
            "talker": "클레이튼",
            "text":"뭐라고?",
            "characterL": {
                "fileName": "Klayton_CG",
                "index": 3
            },
            "characterR": {
                "fileName": "Rex",
                "index": 6
            } 
        },
        {
            "$type": "TalkParagraph, Assembly-CSharp",
            "talker": "클로버",
            "text":"아침에 우연히 클레이튼씨를 만나서 같이 출근했어요.",
            "characterL": {
                "fileName": "Klayton_CG",
                "index": 0
            },
            "characterR": {
                "fileName": "Rex",
                "index": 6
            } 
        },
        {
            "$type": "TalkParagraph, Assembly-CSharp",
            "talker": "렉스",
            "text":"그렇게 된 거였군요.",
            "characterL": {
                "fileName": "Klayton_CG",
                "index": 0
            },
            "characterR": {
                "fileName": "Rex",
                "index": 0
            } 
        },
        {
            "$type": "TalkParagraph, Assembly-CSharp",
            "talker": "클로버",
            "text":"무려 클레이튼씨가 커피도 사주셨다구요?",
            "characterL": {
                "fileName": "Klayton_CG",
                "index": 0
            },
            "characterR": {
                "fileName": "Rex",
                "index": 0
            } 
        },
        {
            "$type": "TalkParagraph, Assembly-CSharp",
            "talker": "렉스",
            "text":"에에? 저는요?",
            "characterL": {
                "fileName": "Klayton_CG",
                "index": 0
            },
            "characterR": {
                "fileName": "Rex",
                "index": 2
            } 
        },
        {
            "$type": "TalkParagraph, Assembly-CSharp",
            "talker": "클레이튼",
            "text":"자네가 뭐가 이쁘다고.",
            "characterL": {
                "fileName": "Klayton_CG",
                "index": 1
            },
            "characterR": {
                "fileName": "Rex",
                "index": 2
            } 
        },
        {
            "$type": "TalkParagraph, Assembly-CSharp",
            "talker": "렉스",
            "text":"그런게 어딨어요? 너무하세요... 부사수를 안챙기고...",
            "characterL": {
                "fileName": "Klayton_CG",
                "index": 1
            },
            "characterR": {
                "fileName": "Rex",
                "index": 2
            } 
        },
        {
            "$type": "TalkParagraph, Assembly-CSharp",
            "talker": "클로버",
            "text":"아. 그럼 저는 받을 자격 없다 라고 말씀하시는 건가요?",
            "characterL": {
                "fileName": "Klayton_CG",
                "index": 1
            },
            "characterR": {
                "fileName": "Rex",
                "index": 2
            } 
        },
        {
            "$type": "TalkParagraph, Assembly-CSharp",
            "talker": "렉스",
            "text":"헉! 아닙니다! 제가 어찌 클로버님께 그런 망언을 하겠습니까.",
            "characterL": {
                "fileName": "Klayton_CG",
                "index": 0
            },
            "characterR": {
                "fileName": "Rex",
                "index": 6
            } 
        },
        {
            "$type": "TalkParagraph, Assembly-CSharp",
            "talker": "클로버",
            "text":"흥, 됐어요. 나중에 비싼 밥 받아먹을 테니, 지갑이나 두둑하게 준비해두세요.",
            "characterL": {
                "fileName": "Klayton_CG",
                "index": 0
            },
            "characterR": {
                "fileName": "Rex",
                "index": 6
            } 
        },
        {
            "$type": "TalkParagraph, Assembly-CSharp",
            "talker": "렉스",
            "text":"넵! 당연합니다.",
            "characterL": {
                "fileName": "Klayton_CG",
                "index": 0
            },
            "characterR": {
                "fileName": "Rex",
                "index": 6
            } 
        },
        {
            "$type": "TalkParagraph, Assembly-CSharp",
            "talker": "클로버",
            "text":"근데 클로버님이 뭐에요. 부담스럽게.",
            "characterL": {
                "fileName": "Klayton_CG",
                "index": 0
            },
            "characterR": {
                "fileName": "Rex",
                "index": 6
            } 
        },
        {
            "$type": "TalkParagraph, Assembly-CSharp",
            "talker": "렉스",
            "text":"그야... 클로버님은 저에게 '신' 이랄까.",
            "characterL": {
                "fileName": "Klayton_CG",
                "index": 0
            },
            "characterR": {
                "fileName": "Rex",
                "index": 5
            } 
        },
        {
            "$type": "TalkParagraph, Assembly-CSharp",
            "talker": "클레이튼",
            "text":"시끄럽고. 둘 다 아침부터 정신없게 하지 말고, 클로버 자네는 자네 근무지로 빨리 가라고.",
            "characterL": {
                "fileName": "Klayton_CG",
                "index": 0
            },
            "characterR": {
                "fileName": "Rex",
                "index": 5
            } 
        },
        {
            "$type": "TalkParagraph, Assembly-CSharp",
            "talker": "클로버",
            "text":"그럼 렉스씨! 다음에 봬요?",
            "characterL": {
                "fileName": "Klayton_CG",
                "index": 0
            },
            "characterR": {
                "fileName": "Rex",
                "index": 3
            } 
        },
        {
            "$type": "TalkParagraph, Assembly-CSharp",
            "talker": "렉스",
            "text":"넵! 연락드리겠습니다.",
            "characterL": {
                "fileName": "Klayton_CG",
                "index": 0
            },
            "characterR": {
                "fileName": "Rex",
                "index": 0
            } 
        },
        {
            "$type": "TalkParagraph, Assembly-CSharp",
            "talker": "클레이튼",
            "text":"자네는 오늘 설명할거 많지 않나? 얼른 시작하지.",
            "characterL": {
                "fileName": "Klayton_CG",
                "index": 0
            },
            "characterR": {
                "fileName": "Rex",
                "index": 0
            } 
        },
        {
            "$type": "TalkParagraph, Assembly-CSharp",
            "talker": "렉스",
            "text":"네. 바로 진행하겠습니다.",
            "characterL": {
                "fileName": "Klayton_CG",
                "index": 0
            },
            "characterR": {
                "fileName": "Rex",
                "index": 4
            } 
        }
    ]
}